Key44.v
module Key44(
  input wire clk,reset, //50MHZ
  input wire [3:0] row, //行
  output reg [3:0] col, //列
  output reg [3:0] key_value //键值
);
reg [5:0] count;  //delay_20ms
reg [2:0] state;  //状态标志
reg key_flag;   //按键标志位
reg clk_500khz;  //500KHZ时钟信号
reg [3:0] col_reg;  //寄存扫描列值
reg [3:0] row_reg;  //寄存扫描行值

initial begin
  col = 0;
  key_value = 4'hz;
  count = 0;
  state = 0;
  key_flag = 0;
  clk_500khz = 0;
  col_reg = 0;
  row_reg = 0;
end

always @(posedge clk or posedge reset)
  if(reset) begin
    clk_500khz<=0;
    count<=0;
  end
  else begin
    if(count>=50) begin clk_500khz<=~clk_500khz;count<=0;end
    else count<=count+1;
  end
always @(posedge clk_500khz or posedge reset)
  if(reset) begin col<=4'b0000;state<=0;end
  else begin
    case (state)
      0:begin
          col[3:0]<=4'b0000;
          key_flag<=1'b0;
          if(row[3:0]!=4'b1111) begin //有键按下，扫描第一行
            state<=1;
            col[3:0]<=4'b1110;
          end
          else state<=0;
        end
      1:begin  //判断是否是第一行
          if(row[3:0]!=4'b1111)
            state<=5;
          else begin
            state<=2;
            col[3:0]<=4'b1101;  //扫描第二行
          end
        end
      2:begin    //判断是否是第二行
          if(row[3:0]!=4'b1111)
            state<=5;
          else begin
            state<=3;
            col[3:0]<=4'b1011;  //扫描第三行
          end
        end
      3:begin    //判断是否是第三一行
          if(row[3:0]!=4'b1111)
            state<=5;
          else begin
            state<=4;  //扫描第四行
            col[3:0]<=4'b0111;
          end
        end
      4:begin //判断是否是第一行
          if(row[3:0]!=4'b1111)
            state<=5;
          else
            state<=0;
        end
      5:begin
          if(row[3:0]!=4'b1111) begin
              col_reg<=col;  //保存扫描列值
              row_reg<=row;  //保存扫描行值
              state<=5;
              key_flag<=1'b1;  //有键按下
            end
          else  state<=0;
        end
      default:begin
          col[3:0]<=4'b0000;
          key_flag<=1'b0;
          if(row[3:0]!=4'b1111) begin //有键按下，扫描第一行
            state<=1;
            col[3:0]<=4'b1110;
          end
          else state<=0;
        end
    endcase
  end
always @(clk_500khz or col_reg or row_reg) begin
  if(key_flag==1'b1)
    begin
      case ({col_reg,row_reg})
        8'b1110_1110:key_value<=0;
        8'b1110_1101:key_value<=1;
        8'b1110_1011:key_value<=2;
        8'b1110_0111:key_value<=3;
        8'b1101_1110:key_value<=4;
        8'b1101_1101:key_value<=5;
        8'b1101_1011:key_value<=6;
        8'b1101_0111:key_value<=7;
        8'b1011_1110:key_value<=8;
        8'b1011_1101:key_value<=9;
        8'b1011_1011:key_value<=10;
        8'b1011_0111:key_value<=11;
        8'b0111_1110:key_value<=12;
        8'b0111_1101:key_value<=13;
        8'b0111_1011:key_value<=14;
        8'b0111_0111:key_value<=15;
      endcase
    end
  else key_value <= 4'hz;
end
endmodule

Key44_t.v
`timescale 10ns/10ns
module K44_test();

reg clk;
initial begin
  clk = 1'b0;
end
always clk = #1 ~clk;
initial
begin
$dumpfile("K44_test.vcd");
$dumpvars(0, K44_test);
end
reg rst;
reg [3:0] row;

initial begin
	rst = 1'b0;
	row = 4'b0000;
end

wire [3:0] col, key_value;

Key44 Key441(
	.clk(clk),
	.reset(rst),
	.row(row),
	.col(col),
	.key_value(key_value)
);

integer count, layout;

initial begin
	count = 0;
	layout = 0;
end


reg [3:0] last_col;

initial last_col = 4'h0;

always @(clk) begin
	case (col)
		4'b0000: row = 4'b1110;
		4'b1110: row = 4'b1111;
		4'b1101: row = 4'b1111;
		4'b1011: row = 4'b1111;
		4'b0111: begin row = 4'b1110; count = count + 1; end
		default: row = 4'b1111;
	endcase
	if(count == 3000) $finish;
end


endmodule // K44_test

K44_test.vcd
$date
	Fri Dec 21 19:02:16 2018
$end
$version
	Icarus Verilog
$end
$timescale
	10ns
$end
$scope module K44_test $end
$var wire 4 ! key_value [3:0] $end
$var wire 4 " col [3:0] $end
$var reg 1 # clk $end
$var reg 4 $ last_col [3:0] $end
$var reg 4 % row [3:0] $end
$var reg 1 & rst $end
$var integer 32 ' count [31:0] $end
$var integer 32 ( layout [31:0] $end
$scope module Key441 $end
$var wire 1 # clk $end
$var wire 1 & reset $end
$var wire 4 ) row [3:0] $end
$var reg 1 * clk_500khz $end
$var reg 4 + col [3:0] $end
$var reg 4 , col_reg [3:0] $end
$var reg 6 - count [5:0] $end
$var reg 1 . key_flag $end
$var reg 4 / key_value [3:0] $end
$var reg 4 0 row_reg [3:0] $end
$var reg 3 1 state [2:0] $end
$upscope $end
$upscope $end
$enddefinitions $end
#0
$dumpvars
b0 1
b0 0
bz /
0.
b0 -
b0 ,
b0 +
0*
b1110 )
b0 (
b0 '
0&
b1110 %
b0 $
0#
b0 "
bz !
$end
#1
b1 -
1#
#2
0#
#3
b10 -
1#
#4
0#
#5
b11 -
1#
#6
0#
#7
b100 -
1#
#8
0#
#9
b101 -
1#
#10
0#
#11
b110 -
1#
#12
0#
#13
b111 -
1#
#14
0#
#15
b1000 -
1#
#16
0#
#17
b1001 -
1#
#18
0#
#19
b1010 -
1#
#20
0#
#21
b1011 -
1#
#22
0#
#23
b1100 -
1#
#24
0#
#25
b1101 -
1#
#26
0#
#27
b1110 -
1#
#28
0#
#29
b1111 -
1#
#30
0#
#31
b10000 -
1#
#32
0#
#33
b10001 -
1#
#34
0#
#35
b10010 -
1#
#36
0#
#37
b10011 -
1#
#38
0#
#39
b10100 -
1#
#40
0#
#41
b10101 -
1#
#42
0#
#43
b10110 -
1#
#44
0#
#45
b10111 -
1#
#46
0#
#47
b11000 -
1#
#48
0#
#49
b11001 -
1#
#50
0#
#51
b11010 -
1#
#52
0#
#53
b11011 -
1#
#54
0#
#55
b11100 -
1#
#56
0#
#57
b11101 -
1#
#58
0#
#59
b11110 -
1#
#60
0#
#61
b11111 -
1#
#62
0#
#63
b100000 -
1#
#64
0#
#65
b100001 -
1#
#66
0#
#67
b100010 -
1#
#68
0#
#69
b100011 -
1#
#70
0#
#71
b100100 -
1#
#72
0#
#73
b100101 -
1#
#74
0#
#75
b100110 -
1#
#76
0#
#77
b100111 -
1#
#78
0#
#79
b101000 -
1#
#80
0#
#81
b101001 -
1#
#82
0#
#83
b101010 -
1#
#84
0#
#85
b101011 -
1#
#86
0#
#87
b101100 -
1#
#88
0#
#89
b101101 -
1#
#90
0#
#91
b101110 -
1#
#92
0#
#93
b101111 -
1#
#94
0#
#95
b110000 -
1#
#96
0#
#97
b110001 -
1#
#98
0#
#99
b110010 -
1#
#100
0#
#101
b1110 "
b1110 +
b1 1
b0 -
1*
1#
#102
b1111 %
b1111 )
0#
#103
b1 -
1#
#104
0#
#105
b10 -
1#
#106
0#
#107
b11 -
1#
#108
0#
#109
b100 -
1#
#110
0#
#111
b101 -
1#
#112
0#
#113
b110 -
1#
#114
0#
#115
b111 -
1#
#116
0#
#117
b1000 -
1#
#118
0#
#119
b1001 -
1#
#120
0#
#121
b1010 -
1#
#122
0#
#123
b1011 -
1#
#124
0#
#125
b1100 -
1#
#126
0#
#127
b1101 -
1#
#128
0#
#129
b1110 -
1#
#130
0#
#131
b1111 -
1#
#132
0#
#133
b10000 -
1#
#134
0#
#135
b10001 -
1#
#136
0#
#137
b10010 -
1#
#138
0#
#139
b10011 -
1#
#140
0#
#141
b10100 -
1#
#142
0#
#143
b10101 -
1#
#144
0#
#145
b10110 -
1#
#146
0#
#147
b10111 -
1#
#148
0#
#149
b11000 -
1#
#150
0#
#151
b11001 -
1#
#152
0#
#153
b11010 -
1#
#154
0#
#155
b11011 -
1#
#156
0#
#157
b11100 -
1#
#158
0#
#159
b11101 -
1#
#160
0#
#161
b11110 -
1#
#162
0#
#163
b11111 -
1#
#164
0#
#165
b100000 -
1#
#166
0#
#167
b100001 -
1#
#168
0#
#169
b100010 -
1#
#170
0#
#171
b100011 -
1#
#172
0#
#173
b100100 -
1#
#174
0#
#175
b100101 -
1#
#176
0#
#177
b100110 -
1#
#178
0#
#179
b100111 -
1#
#180
0#
#181
b101000 -
1#
#182
0#
#183
b101001 -
1#
#184
0#
#185
b101010 -
1#
#186
0#
#187
b101011 -
1#
#188
0#
#189
b101100 -
1#
#190
0#
#191
b101101 -
1#
#192
0#
#193
b101110 -
1#
#194
0#
#195
b101111 -
1#
#196
0#
#197
b110000 -
1#
#198
0#
#199
b110001 -
1#
#200
0#
#201
b110010 -
1#
#202
0#
#203
b0 -
0*
1#
#204
0#
#205
b1 -
1#
#206
0#
#207
b10 -
1#
#208
0#
#209
b11 -
1#
#210
0#
#211
b100 -
1#
#212
0#
#213
b101 -
1#
#214
0#
#215
b110 -
1#
#216
0#
#217
b111 -
1#
#218
0#
#219
b1000 -
1#
#220
0#
#221
b1001 -
1#
#222
0#
#223
b1010 -
1#
#224
0#
#225
b1011 -
1#
#226
0#
#227
b1100 -
1#
#228
0#
#229
b1101 -
1#
#230
0#
#231
b1110 -
1#
#232
0#
#233
b1111 -
1#
#234
0#
#235
b10000 -
1#
#236
0#
#237
b10001 -
1#
#238
0#
#239
b10010 -
1#
#240
0#
#241
b10011 -
1#
#242
0#
#243
b10100 -
1#
#244
0#
#245
b10101 -
1#
#246
0#
#247
b10110 -
1#
#248
0#
#249
b10111 -
1#
#250
0#
#251
b11000 -
1#
#252
0#
#253
b11001 -
1#
#254
0#
#255
b11010 -
1#
#256
0#
#257
b11011 -
1#
#258
0#
#259
b11100 -
1#
#260
0#
#261
b11101 -
1#
#262
0#
#263
b11110 -
1#
#264
0#
#265
b11111 -
1#
#266
0#
#267
b100000 -
1#
#268
0#
#269
b100001 -
1#
#270
0#
#271
b100010 -
1#
#272
0#
#273
b100011 -
1#
#274
0#
#275
b100100 -
1#
#276
0#
#277
b100101 -
1#
#278
0#
#279
b100110 -
1#
#280
0#
#281
b100111 -
1#
#282
0#
#283
b101000 -
1#
#284
0#
#285
b101001 -
1#
#286
0#
#287
b101010 -
1#
#288
0#
#289
b101011 -
1#
#290
0#
#291
b101100 -
1#
#292
0#
#293
b101101 -
1#
#294
0#
#295
b101110 -
1#
#296
0#
#297
b101111 -
1#
#298
0#
#299
b110000 -
1#
#300
0#
#301
b110001 -
1#
#302
0#
#303
b110010 -
1#
#304
0#
#305
b1101 "
b1101 +
b10 1
b0 -
1*
1#
#306
0#
#307
b1 -
1#
#308
0#
#309
b10 -
1#
#310
0#
#311
b11 -
1#
#312
0#
#313
b100 -
1#
#314
0#
#315
b101 -
1#
#316
0#
#317
b110 -
1#
#318
0#
#319
b111 -
1#
#320
0#
#321
b1000 -
1#
#322
0#
#323
b1001 -
1#
#324
0#
#325
b1010 -
1#
#326
0#
#327
b1011 -
1#
#328
0#
#329
b1100 -
1#
#330
0#
#331
b1101 -
1#
#332
0#
#333
b1110 -
1#
#334
0#
#335
b1111 -
1#
#336
0#
#337
b10000 -
1#
#338
0#
#339
b10001 -
1#
#340
0#
#341
b10010 -
1#
#342
0#
#343
b10011 -
1#
#344
0#
#345
b10100 -
1#
#346
0#
#347
b10101 -
1#
#348
0#
#349
b10110 -
1#
#350
0#
#351
b10111 -
1#
#352
0#
#353
b11000 -
1#
#354
0#
#355
b11001 -
1#
#356
0#
#357
b11010 -
1#
#358
0#
#359
b11011 -
1#
#360
0#
#361
b11100 -
1#
#362
0#
#363
b11101 -
1#
#364
0#
#365
b11110 -
1#
#366
0#
#367
b11111 -
1#
#368
0#
#369
b100000 -
1#
#370
0#
#371
b100001 -
1#
#372
0#
#373
b100010 -
1#
#374
0#
#375
b100011 -
1#
#376
0#
#377
b100100 -
1#
#378
0#
#379
b100101 -
1#
#380
0#
#381
b100110 -
1#
#382
0#
#383
b100111 -
1#
#384
0#
#385
b101000 -
1#
#386
0#
#387
b101001 -
1#
#388
0#
#389
b101010 -
1#
#390
0#
#391
b101011 -
1#
#392
0#
#393
b101100 -
1#
#394
0#
#395
b101101 -
1#
#396
0#
#397
b101110 -
1#
#398
0#
#399
b101111 -
1#
#400
0#
#401
b110000 -
1#
#402
0#
#403
b110001 -
1#
#404
0#
#405
b110010 -
1#
#406
0#
#407
b0 -
0*
1#
#408
0#
#409
b1 -
1#
#410
0#
#411
b10 -
1#
#412
0#
#413
b11 -
1#
#414
0#
#415
b100 -
1#
#416
0#
#417
b101 -
1#
#418
0#
#419
b110 -
1#
#420
0#
#421
b111 -
1#
#422
0#
#423
b1000 -
1#
#424
0#
#425
b1001 -
1#
#426
0#
#427
b1010 -
1#
#428
0#
#429
b1011 -
1#
#430
0#
#431
b1100 -
1#
#432
0#
#433
b1101 -
1#
#434
0#
#435
b1110 -
1#
#436
0#
#437
b1111 -
1#
#438
0#
#439
b10000 -
1#
#440
0#
#441
b10001 -
1#
#442
0#
#443
b10010 -
1#
#444
0#
#445
b10011 -
1#
#446
0#
#447
b10100 -
1#
#448
0#
#449
b10101 -
1#
#450
0#
#451
b10110 -
1#
#452
0#
#453
b10111 -
1#
#454
0#
#455
b11000 -
1#
#456
0#
#457
b11001 -
1#
#458
0#
#459
b11010 -
1#
#460
0#
#461
b11011 -
1#
#462
0#
#463
b11100 -
1#
#464
0#
#465
b11101 -
1#
#466
0#
#467
b11110 -
1#
#468
0#
#469
b11111 -
1#
#470
0#
#471
b100000 -
1#
#472
0#
#473
b100001 -
1#
#474
0#
#475
b100010 -
1#
#476
0#
#477
b100011 -
1#
#478
0#
#479
b100100 -
1#
#480
0#
#481
b100101 -
1#
#482
0#
#483
b100110 -
1#
#484
0#
#485
b100111 -
1#
#486
0#
#487
b101000 -
1#
#488
0#
#489
b101001 -
1#
#490
0#
#491
b101010 -
1#
#492
0#
#493
b101011 -
1#
#494
0#
#495
b101100 -
1#
#496
0#
#497
b101101 -
1#
#498
0#
#499
b101110 -
1#
#500
0#
#501
b101111 -
1#
#502
0#
#503
b110000 -
1#
#504
0#
#505
b110001 -
1#
#506
0#
#507
b110010 -
1#
#508
0#
#509
b1011 "
b1011 +
b11 1
b0 -
1*
1#
#510
0#
#511
b1 -
1#
#512
0#
#513
b10 -
1#
#514
0#
#515
b11 -
1#
#516
0#
#517
b100 -
1#
#518
0#
#519
b101 -
1#
#520
0#
#521
b110 -
1#
#522
0#
#523
b111 -
1#
#524
0#
#525
b1000 -
1#
#526
0#
#527
b1001 -
1#
#528
0#
#529
b1010 -
1#
#530
0#
#531
b1011 -
1#
#532
0#
#533
b1100 -
1#
#534
0#
#535
b1101 -
1#
#536
0#
#537
b1110 -
1#
#538
0#
#539
b1111 -
1#
#540
0#
#541
b10000 -
1#
#542
0#
#543
b10001 -
1#
#544
0#
#545
b10010 -
1#
#546
0#
#547
b10011 -
1#
#548
0#
#549
b10100 -
1#
#550
0#
#551
b10101 -
1#
#552
0#
#553
b10110 -
1#
#554
0#
#555
b10111 -
1#
#556
0#
#557
b11000 -
1#
#558
0#
#559
b11001 -
1#
#560
0#
#561
b11010 -
1#
#562
0#
#563
b11011 -
1#
#564
0#
#565
b11100 -
1#
#566
0#
#567
b11101 -
1#
#568
0#
#569
b11110 -
1#
#570
0#
#571
b11111 -
1#
#572
0#
#573
b100000 -
1#
#574
0#
#575
b100001 -
1#
#576
0#
#577
b100010 -
1#
#578
0#
#579
b100011 -
1#
#580
0#
#581
b100100 -
1#
#582
0#
#583
b100101 -
1#
#584
0#
#585
b100110 -
1#
#586
0#
#587
b100111 -
1#
#588
0#
#589
b101000 -
1#
#590
0#
#591
b101001 -
1#
#592
0#
#593
b101010 -
1#
#594
0#
#595
b101011 -
1#
#596
0#
#597
b101100 -
1#
#598
0#
#599
b101101 -
1#
#600
0#
#601
b101110 -
1#
#602
0#
#603
b101111 -
1#
#604
0#
#605
b110000 -
1#
#606
0#
#607
b110001 -
1#
#608
0#
#609
b110010 -
1#
#610
0#
#611
b0 -
0*
1#
#612
0#
#613
b1 -
1#
#614
0#
#615
b10 -
1#
#616
0#
#617
b11 -
1#
#618
0#
#619
b100 -
1#
#620
0#
#621
b101 -
1#
#622
0#
#623
b110 -
1#
#624
0#
#625
b111 -
1#
#626
0#
#627
b1000 -
1#
#628
0#
#629
b1001 -
1#
#630
0#
#631
b1010 -
1#
#632
0#
#633
b1011 -
1#
#634
0#
#635
b1100 -
1#
#636
0#
#637
b1101 -
1#
#638
0#
#639
b1110 -
1#
#640
0#
#641
b1111 -
1#
#642
0#
#643
b10000 -
1#
#644
0#
#645
b10001 -
1#
#646
0#
#647
b10010 -
1#
#648
0#
#649
b10011 -
1#
#650
0#
#651
b10100 -
1#
#652
0#
#653
b10101 -
1#
#654
0#
#655
b10110 -
1#
#656
0#
#657
b10111 -
1#
#658
0#
#659
b11000 -
1#
#660
0#
#661
b11001 -
1#
#662
0#
#663
b11010 -
1#
#664
0#
#665
b11011 -
1#
#666
0#
#667
b11100 -
1#
#668
0#
#669
b11101 -
1#
#670
0#
#671
b11110 -
1#
#672
0#
#673
b11111 -
1#
#674
0#
#675
b100000 -
1#
#676
0#
#677
b100001 -
1#
#678
0#
#679
b100010 -
1#
#680
0#
#681
b100011 -
1#
#682
0#
#683
b100100 -
1#
#684
0#
#685
b100101 -
1#
#686
0#
#687
b100110 -
1#
#688
0#
#689
b100111 -
1#
#690
0#
#691
b101000 -
1#
#692
0#
#693
b101001 -
1#
#694
0#
#695
b101010 -
1#
#696
0#
#697
b101011 -
1#
#698
0#
#699
b101100 -
1#
#700
0#
#701
b101101 -
1#
#702
0#
#703
b101110 -
1#
#704
0#
#705
b101111 -
1#
#706
0#
#707
b110000 -
1#
#708
0#
#709
b110001 -
1#
#710
0#
#711
b110010 -
1#
#712
0#
#713
b111 "
b111 +
b100 1
b0 -
1*
1#
#714
b1 '
b1110 %
b1110 )
0#
#715
b1 -
b10 '
1#
#716
b11 '
0#
#717
b10 -
b100 '
1#
#718
b101 '
0#
#719
b11 -
b110 '
1#
#720
b111 '
0#
#721
b100 -
b1000 '
1#
#722
b1001 '
0#
#723
b101 -
b1010 '
1#
#724
b1011 '
0#
#725
b110 -
b1100 '
1#
#726
b1101 '
0#
#727
b111 -
b1110 '
1#
#728
b1111 '
0#
#729
b1000 -
b10000 '
1#
#730
b10001 '
0#
#731
b1001 -
b10010 '
1#
#732
b10011 '
0#
#733
b1010 -
b10100 '
1#
#734
b10101 '
0#
#735
b1011 -
b10110 '
1#
#736
b10111 '
0#
#737
b1100 -
b11000 '
1#
#738
b11001 '
0#
#739
b1101 -
b11010 '
1#
#740
b11011 '
0#
#741
b1110 -
b11100 '
1#
#742
b11101 '
0#
#743
b1111 -
b11110 '
1#
#744
b11111 '
0#
#745
b10000 -
b100000 '
1#
#746
b100001 '
0#
#747
b10001 -
b100010 '
1#
#748
b100011 '
0#
#749
b10010 -
b100100 '
1#
#750
b100101 '
0#
#751
b10011 -
b100110 '
1#
#752
b100111 '
0#
#753
b10100 -
b101000 '
1#
#754
b101001 '
0#
#755
b10101 -
b101010 '
1#
#756
b101011 '
0#
#757
b10110 -
b101100 '
1#
#758
b101101 '
0#
#759
b10111 -
b101110 '
1#
#760
b101111 '
0#
#761
b11000 -
b110000 '
1#
#762
b110001 '
0#
#763
b11001 -
b110010 '
1#
#764
b110011 '
0#
#765
b11010 -
b110100 '
1#
#766
b110101 '
0#
#767
b11011 -
b110110 '
1#
#768
b110111 '
0#
#769
b11100 -
b111000 '
1#
#770
b111001 '
0#
#771
b11101 -
b111010 '
1#
#772
b111011 '
0#
#773
b11110 -
b111100 '
1#
#774
b111101 '
0#
#775
b11111 -
b111110 '
1#
#776
b111111 '
0#
#777
b100000 -
b1000000 '
1#
#778
b1000001 '
0#
#779
b100001 -
b1000010 '
1#
#780
b1000011 '
0#
#781
b100010 -
b1000100 '
1#
#782
b1000101 '
0#
#783
b100011 -
b1000110 '
1#
#784
b1000111 '
0#
#785
b100100 -
b1001000 '
1#
#786
b1001001 '
0#
#787
b100101 -
b1001010 '
1#
#788
b1001011 '
0#
#789
b100110 -
b1001100 '
1#
#790
b1001101 '
0#
#791
b100111 -
b1001110 '
1#
#792
b1001111 '
0#
#793
b101000 -
b1010000 '
1#
#794
b1010001 '
0#
#795
b101001 -
b1010010 '
1#
#796
b1010011 '
0#
#797
b101010 -
b1010100 '
1#
#798
b1010101 '
0#
#799
b101011 -
b1010110 '
1#
#800
b1010111 '
0#
#801
b101100 -
b1011000 '
1#
#802
b1011001 '
0#
#803
b101101 -
b1011010 '
1#
#804
b1011011 '
0#
#805
b101110 -
b1011100 '
1#
#806
b1011101 '
0#
#807
b101111 -
b1011110 '
1#
#808
b1011111 '
0#
#809
b110000 -
b1100000 '
1#
#810
b1100001 '
0#
#811
b110001 -
b1100010 '
1#
#812
b1100011 '
0#
#813
b110010 -
b1100100 '
1#
#814
b1100101 '
0#
#815
b0 -
0*
b1100110 '
1#
#816
b1100111 '
0#
#817
b1 -
b1101000 '
1#
#818
b1101001 '
0#
#819
b10 -
b1101010 '
1#
#820
b1101011 '
0#
#821
b11 -
b1101100 '
1#
#822
b1101101 '
0#
#823
b100 -
b1101110 '
1#
#824
b1101111 '
0#
#825
b101 -
b1110000 '
1#
#826
b1110001 '
0#
#827
b110 -
b1110010 '
1#
#828
b1110011 '
0#
#829
b111 -
b1110100 '
1#
#830
b1110101 '
0#
#831
b1000 -
b1110110 '
1#
#832
b1110111 '
0#
#833
b1001 -
b1111000 '
1#
#834
b1111001 '
0#
#835
b1010 -
b1111010 '
1#
#836
b1111011 '
0#
#837
b1011 -
b1111100 '
1#
#838
b1111101 '
0#
#839
b1100 -
b1111110 '
1#
#840
b1111111 '
0#
#841
b1101 -
b10000000 '
1#
#842
b10000001 '
0#
#843
b1110 -
b10000010 '
1#
#844
b10000011 '
0#
#845
b1111 -
b10000100 '
1#
#846
b10000101 '
0#
#847
b10000 -
b10000110 '
1#
#848
b10000111 '
0#
#849
b10001 -
b10001000 '
1#
#850
b10001001 '
0#
#851
b10010 -
b10001010 '
1#
#852
b10001011 '
0#
#853
b10011 -
b10001100 '
1#
#854
b10001101 '
0#
#855
b10100 -
b10001110 '
1#
#856
b10001111 '
0#
#857
b10101 -
b10010000 '
1#
#858
b10010001 '
0#
#859
b10110 -
b10010010 '
1#
#860
b10010011 '
0#
#861
b10111 -
b10010100 '
1#
#862
b10010101 '
0#
#863
b11000 -
b10010110 '
1#
#864
b10010111 '
0#
#865
b11001 -
b10011000 '
1#
#866
b10011001 '
0#
#867
b11010 -
b10011010 '
1#
#868
b10011011 '
0#
#869
b11011 -
b10011100 '
1#
#870
b10011101 '
0#
#871
b11100 -
b10011110 '
1#
#872
b10011111 '
0#
#873
b11101 -
b10100000 '
1#
#874
b10100001 '
0#
#875
b11110 -
b10100010 '
1#
#876
b10100011 '
0#
#877
b11111 -
b10100100 '
1#
#878
b10100101 '
0#
#879
b100000 -
b10100110 '
1#
#880
b10100111 '
0#
#881
b100001 -
b10101000 '
1#
#882
b10101001 '
0#
#883
b100010 -
b10101010 '
1#
#884
b10101011 '
0#
#885
b100011 -
b10101100 '
1#
#886
b10101101 '
0#
#887
b100100 -
b10101110 '
1#
#888
b10101111 '
0#
#889
b100101 -
b10110000 '
1#
#890
b10110001 '
0#
#891
b100110 -
b10110010 '
1#
#892
b10110011 '
0#
#893
b100111 -
b10110100 '
1#
#894
b10110101 '
0#
#895
b101000 -
b10110110 '
1#
#896
b10110111 '
0#
#897
b101001 -
b10111000 '
1#
#898
b10111001 '
0#
#899
b101010 -
b10111010 '
1#
#900
b10111011 '
0#
#901
b101011 -
b10111100 '
1#
#902
b10111101 '
0#
#903
b101100 -
b10111110 '
1#
#904
b10111111 '
0#
#905
b101101 -
b11000000 '
1#
#906
b11000001 '
0#
#907
b101110 -
b11000010 '
1#
#908
b11000011 '
0#
#909
b101111 -
b11000100 '
1#
#910
b11000101 '
0#
#911
b110000 -
b11000110 '
1#
#912
b11000111 '
0#
#913
b110001 -
b11001000 '
1#
#914
b11001001 '
0#
#915
b110010 -
b11001010 '
1#
#916
b11001011 '
0#
#917
b101 1
b0 -
1*
b11001100 '
1#
#918
b11001101 '
0#
#919
b1 -
b11001110 '
1#
#920
b11001111 '
0#
#921
b10 -
b11010000 '
1#
#922
b11010001 '
0#
#923
b11 -
b11010010 '
1#
#924
b11010011 '
0#
#925
b100 -
b11010100 '
1#
#926
b11010101 '
0#
#927
b101 -
b11010110 '
1#
#928
b11010111 '
0#
#929
b110 -
b11011000 '
1#
#930
b11011001 '
0#
#931
b111 -
b11011010 '
1#
#932
b11011011 '
0#
#933
b1000 -
b11011100 '
1#
#934
b11011101 '
0#
#935
b1001 -
b11011110 '
1#
#936
b11011111 '
0#
#937
b1010 -
b11100000 '
1#
#938
b11100001 '
0#
#939
b1011 -
b11100010 '
1#
#940
b11100011 '
0#
#941
b1100 -
b11100100 '
1#
#942
b11100101 '
0#
#943
b1101 -
b11100110 '
1#
#944
b11100111 '
0#
#945
b1110 -
b11101000 '
1#
#946
b11101001 '
0#
#947
b1111 -
b11101010 '
1#
#948
b11101011 '
0#
#949
b10000 -
b11101100 '
1#
#950
b11101101 '
0#
#951
b10001 -
b11101110 '
1#
#952
b11101111 '
0#
#953
b10010 -
b11110000 '
1#
#954
b11110001 '
0#
#955
b10011 -
b11110010 '
1#
#956
b11110011 '
0#
#957
b10100 -
b11110100 '
1#
#958
b11110101 '
0#
#959
b10101 -
b11110110 '
1#
#960
b11110111 '
0#
#961
b10110 -
b11111000 '
1#
#962
b11111001 '
0#
#963
b10111 -
b11111010 '
1#
#964
b11111011 '
0#
#965
b11000 -
b11111100 '
1#
#966
b11111101 '
0#
#967
b11001 -
b11111110 '
1#
#968
b11111111 '
0#
#969
b11010 -
b100000000 '
1#
#970
b100000001 '
0#
#971
b11011 -
b100000010 '
1#
#972
b100000011 '
0#
#973
b11100 -
b100000100 '
1#
#974
b100000101 '
0#
#975
b11101 -
b100000110 '
1#
#976
b100000111 '
0#
#977
b11110 -
b100001000 '
1#
#978
b100001001 '
0#
#979
b11111 -
b100001010 '
1#
#980
b100001011 '
0#
#981
b100000 -
b100001100 '
1#
#982
b100001101 '
0#
#983
b100001 -
b100001110 '
1#
#984
b100001111 '
0#
#985
b100010 -
b100010000 '
1#
#986
b100010001 '
0#
#987
b100011 -
b100010010 '
1#
#988
b100010011 '
0#
#989
b100100 -
b100010100 '
1#
#990
b100010101 '
0#
#991
b100101 -
b100010110 '
1#
#992
b100010111 '
0#
#993
b100110 -
b100011000 '
1#
#994
b100011001 '
0#
#995
b100111 -
b100011010 '
1#
#996
b100011011 '
0#
#997
b101000 -
b100011100 '
1#
#998
b100011101 '
0#
#999
b101001 -
b100011110 '
1#
#1000
b100011111 '
0#
#1001
b101010 -
b100100000 '
1#
#1002
b100100001 '
0#
#1003
b101011 -
b100100010 '
1#
#1004
b100100011 '
0#
#1005
b101100 -
b100100100 '
1#
#1006
b100100101 '
0#
#1007
b101101 -
b100100110 '
1#
#1008
b100100111 '
0#
#1009
b101110 -
b100101000 '
1#
#1010
b100101001 '
0#
#1011
b101111 -
b100101010 '
1#
#1012
b100101011 '
0#
#1013
b110000 -
b100101100 '
1#
#1014
b100101101 '
0#
#1015
b110001 -
b100101110 '
1#
#1016
b100101111 '
0#
#1017
b110010 -
b100110000 '
1#
#1018
b100110001 '
0#
#1019
b0 -
0*
b100110010 '
1#
#1020
b100110011 '
0#
#1021
b1 -
b100110100 '
1#
#1022
b100110101 '
0#
#1023
b10 -
b100110110 '
1#
#1024
b100110111 '
0#
#1025
b11 -
b100111000 '
1#
#1026
b100111001 '
0#
#1027
b100 -
b100111010 '
1#
#1028
b100111011 '
0#
#1029
b101 -
b100111100 '
1#
#1030
b100111101 '
0#
#1031
b110 -
b100111110 '
1#
#1032
b100111111 '
0#
#1033
b111 -
b101000000 '
1#
#1034
b101000001 '
0#
#1035
b1000 -
b101000010 '
1#
#1036
b101000011 '
0#
#1037
b1001 -
b101000100 '
1#
#1038
b101000101 '
0#
#1039
b1010 -
b101000110 '
1#
#1040
b101000111 '
0#
#1041
b1011 -
b101001000 '
1#
#1042
b101001001 '
0#
#1043
b1100 -
b101001010 '
1#
#1044
b101001011 '
0#
#1045
b1101 -
b101001100 '
1#
#1046
b101001101 '
0#
#1047
b1110 -
b101001110 '
1#
#1048
b101001111 '
0#
#1049
b1111 -
b101010000 '
1#
#1050
b101010001 '
0#
#1051
b10000 -
b101010010 '
1#
#1052
b101010011 '
0#
#1053
b10001 -
b101010100 '
1#
#1054
b101010101 '
0#
#1055
b10010 -
b101010110 '
1#
#1056
b101010111 '
0#
#1057
b10011 -
b101011000 '
1#
#1058
b101011001 '
0#
#1059
b10100 -
b101011010 '
1#
#1060
b101011011 '
0#
#1061
b10101 -
b101011100 '
1#
#1062
b101011101 '
0#
#1063
b10110 -
b101011110 '
1#
#1064
b101011111 '
0#
#1065
b10111 -
b101100000 '
1#
#1066
b101100001 '
0#
#1067
b11000 -
b101100010 '
1#
#1068
b101100011 '
0#
#1069
b11001 -
b101100100 '
1#
#1070
b101100101 '
0#
#1071
b11010 -
b101100110 '
1#
#1072
b101100111 '
0#
#1073
b11011 -
b101101000 '
1#
#1074
b101101001 '
0#
#1075
b11100 -
b101101010 '
1#
#1076
b101101011 '
0#
#1077
b11101 -
b101101100 '
1#
#1078
b101101101 '
0#
#1079
b11110 -
b101101110 '
1#
#1080
b101101111 '
0#
#1081
b11111 -
b101110000 '
1#
#1082
b101110001 '
0#
#1083
b100000 -
b101110010 '
1#
#1084
b101110011 '
0#
#1085
b100001 -
b101110100 '
1#
#1086
b101110101 '
0#
#1087
b100010 -
b101110110 '
1#
#1088
b101110111 '
0#
#1089
b100011 -
b101111000 '
1#
#1090
b101111001 '
0#
#1091
b100100 -
b101111010 '
1#
#1092
b101111011 '
0#
#1093
b100101 -
b101111100 '
1#
#1094
b101111101 '
0#
#1095
b100110 -
b101111110 '
1#
#1096
b101111111 '
0#
