commend.v
`define MEMORYSIZE 2
module commend(
  input clk,
  input nst,
  input [3:0] key_value,
  output reg [5:0] address,
  input wire timeout,
  output reg commend,
  output reg timecheckstop,
  output reg NVcommend,
  inout [`MEMORYSIZE-1:0] data
);

wire [`MEMORYSIZE-1:0] data_in;

reg [`MEMORYSIZE-1:0] data_out;

assign data = ~commend ? data_out : {`MEMORYSIZE{1'bz}};
assign data_in = commend ? data : {`MEMORYSIZE{1'bz}};

reg [4:0] status;
reg [3:0] key_value_tmp;
reg [5:0] k;

reg [20:0] cnt;

reg [1:0] OtherStatus;

initial begin
  status = 0;
  address = {6{1'bz}};
  commend = 1'bz;
  NVcommend = 1'b1;
  OtherStatus = 0;
  k = 0;
  cnt = 0;
  key_value_tmp = 4'hz;
  timecheckstop = 1'b1;
end

always @(posedge clk or posedge nst) begin
  if(nst)begin
    status <= 0;
    address <= {6{1'bz}};
    commend <= 1'bz;
    NVcommend <= 1'b1;
    OtherStatus <= 0;
    k <= 0;
    cnt <= 0;
    key_value_tmp <= 4'hz;
    timecheckstop <= 1'b1;
  end
  else if(timeout)begin
    timecheckstop <= 1'b1;
    cnt <= cnt + 1;
    if(cnt == 0)begin
      if(k == 0) OtherStatus <= OtherStatus + 1;
      if(OtherStatus == 2) begin
        commend <= 1'bz;
        address <= {6{1'bz}};
        NVcommend <= 1'b1;
      end
      else begin
        address <= k;
        data_out <= 1;
        k <= k + 1;
        NVcommend <= 1'b0;
        commend <= 1'b0;
      end
    end
    else begin
      commend <= 1'bz;
      address <= {6{1'bz}};
      NVcommend <= 1'b1;
    end
  end
  else
    case (status)
      0: begin // 等待键盘
      if(!(key_value_tmp === key_value))begin
        timecheckstop <= 1'b0;
        case (key_value)
          7:begin
            key_value_tmp <= key_value;
            NVcommend <= 1'b0;
            address <= k;
            commend <= 1'b1;
            status <= 1;
          end
          5:begin
            key_value_tmp <= key_value;
            NVcommend <= 1'b0;
            address <= k;
            commend <= 1'b1;
            status <= 1;
          end
          2:begin
            key_value_tmp <= key_value;
            NVcommend <= 1'b0;
            address <= k;
            commend <= 1'b1;
            status <= 1;
          end
          10:begin
            key_value_tmp <= key_value;
            NVcommend <= 1'b0;
            address <= k;
            commend <= 1'b1;
            status <= 1;
          end
          default: begin
            key_value_tmp <= 4'hz;
            NVcommend <= 1'b1;
            address <= {6{1'bz}};
            commend <= 1'bz;
          end 
        endcase
      end
      end
      1:begin // 找人
        if(data_in == 2)begin
          status <= 2;
        end
        else begin
          k <= k + 1;
          address <= k + 1;
        end
      end
      2:begin //看墙
        case (key_value_tmp)
          7:begin
            address[5:3] <= address[5:3] - 1'b1;
          end
          5:begin
            address[5:3] <= address[5:3] + 1'b1;
          end
          2:begin
            address[2:0] <= address[2:0] - 1'b1;
          end
          10:begin
            address[2:0] <= address[2:0] + 1'b1;
          end
          default: status <= 0;
        endcase
        status <= 3;
      end
      3:begin //撞墙
        case (data_in)
          0:begin
            if(address[2:0] == 3'b111)begin
              timecheckstop <= 1'b1;
              status <= 6;
            end
            else begin
              commend <= 1'b0;
              data_out <= 2;
              status <= 4;
            end
          end
          1:begin
            status <= 0;
          end 
          default: status <= 0;
        endcase
      end
      4:begin // 走
        address <= k;
        data_out  <= 0;
        status <= 5;
        k <= 0;
        OtherStatus <= 0;
      end
      5:begin //恢复
        status <= 0;
        address <= {6{1'bz}};
        commend <= 1'bz;
        NVcommend <= 1'b1;
        k <= 0;
        // key_value_tmp <= 4'hz;
      end
      6:begin //赢了
        cnt <= cnt + 1;
        if(cnt == 0)begin
          if(k == 0) OtherStatus <= OtherStatus + 1;
          if(OtherStatus == 2) status <= 7;
          address <= k;
          data_out <= 2;
          k <= k + 1;
          NVcommend <= 1'b0;
          commend <= 1'b0;
        end
        else begin
          commend <= 1'bz;
          address <= {6{1'bz}};
          NVcommend <= 1'b1;
        end
      end
      7: begin //结束
        commend <= 1'bz;
        address <= {6{1'bz}};
        NVcommend <= 1'b1;
      end
      default: status <= 0;
    endcase
end

endmodule // commend

memory.v
`define MEMORYSIZE 2
module memory(
  input clk, // 50Mhz
  input rst,
  input [5:0] address,
  input command,
  inout [`MEMORYSIZE-1:0] data
);
reg count;
reg [`MEMORYSIZE-1:0] mem [63:0];

initial begin
  count = 1'b0;
  mem[0] = 2'b1;
  mem[1] = 2'b1;
  mem[2] = 2'b1;
  mem[3] = 2'b1;
  mem[4] = 2'b1;
  mem[5] = 2'b1;
  mem[6] = 2'b1;
  mem[7] = 2'b1;
  mem[8] = 2'b1;
  mem[9] = 2'b1;
  mem[10] = 2'b1;
  mem[11] = 2'b1;
  mem[12] = 2'b0;
  mem[13] = 2'b0;
  mem[14] = 2'b0;
  mem[15] = 2'b1;
  mem[16] = 2'b1;
  mem[17] = 2'b0;
  mem[18] = 2'b0;
  mem[19] = 2'b0;
  mem[20] = 2'b0;
  mem[21] = 2'b1;
  mem[22] = 2'b0;
  mem[23] = 2'b1;
  mem[24] = 2'b1;
  mem[25] = 2'b0;
  mem[26] = 2'b1;
  mem[27] = 2'b0;
  mem[28] = 2'b1;
  mem[29] = 2'b1;
  mem[30] = 2'b0;
  mem[31] = 2'b1;
  mem[32] = 2'b1;
  mem[33] = 2'b0;
  mem[34] = 2'b1;
  mem[35] = 2'b0;
  mem[36] = 2'b1;
  mem[37] = 2'b0;
  mem[38] = 2'b0;
  mem[39] = 2'b1;
  mem[40] = 2'b1;
  mem[41] = 2'b0;
  mem[42] = 2'b1;
  mem[43] = 2'b0;
  mem[44] = 2'b1;
  mem[45] = 2'b0;
  mem[46] = 2'b1;
  mem[47] = 2'b1;
  mem[48] = 2'b10;
  mem[49] = 2'b0;
  mem[50] = 2'b1;
  mem[51] = 2'b1;
  mem[52] = 2'b1;
  mem[53] = 2'b0;
  mem[54] = 2'b0;
  mem[55] = 2'b0;
  mem[56] = 2'b1;
  mem[57] = 2'b1;
  mem[58] = 2'b1;
  mem[59] = 2'b1;
  mem[60] = 2'b1;
  mem[61] = 2'b1;
  mem[62] = 2'b1;
  mem[63] = 2'b1;
end

wire [`MEMORYSIZE-1:0] data_in;

assign data_in = ~command ? data : {`MEMORYSIZE{1'bz}};

// assign data = 2'b1;
assign data = command ? mem[address] : {`MEMORYSIZE{1'bz}};

always @(posedge clk or posedge rst) begin
  count <= ~count;
  if (rst) begin
    case (address[0]^address[1]^address[3])
      1'b0:begin
        mem[0] = 2'b1;
        mem[1] = 2'b1;
        mem[2] = 2'b1;
        mem[3] = 2'b1;
        mem[4] = 2'b1;
        mem[5] = 2'b1;
        mem[6] = 2'b1;
        mem[7] = 2'b1;
        mem[8] = 2'b1;
        mem[9] = 2'b1;
        mem[10] = 2'b1;
        mem[11] = 2'b1;
        mem[12] = 2'b0;
        mem[13] = 2'b0;
        mem[14] = 2'b0;
        mem[15] = 2'b1;
        mem[16] = 2'b1;
        mem[17] = 2'b0;
        mem[18] = 2'b0;
        mem[19] = 2'b0;
        mem[20] = 2'b0;
        mem[21] = 2'b1;
        mem[22] = 2'b0;
        mem[23] = 2'b1;
        mem[24] = 2'b1;
        mem[25] = 2'b0;
        mem[26] = 2'b1;
        mem[27] = 2'b0;
        mem[28] = 2'b1;
        mem[29] = 2'b1;
        mem[30] = 2'b0;
        mem[31] = 2'b1;
        mem[32] = 2'b1;
        mem[33] = 2'b0;
        mem[34] = 2'b1;
        mem[35] = 2'b0;
        mem[36] = 2'b1;
        mem[37] = 2'b0;
        mem[38] = 2'b0;
        mem[39] = 2'b1;
        mem[40] = 2'b1;
        mem[41] = 2'b0;
        mem[42] = 2'b1;
        mem[43] = 2'b0;
        mem[44] = 2'b1;
        mem[45] = 2'b0;
        mem[46] = 2'b1;
        mem[47] = 2'b1;
        mem[48] = 2'b10;
        mem[49] = 2'b0;
        mem[50] = 2'b1;
        mem[51] = 2'b1;
        mem[52] = 2'b1;
        mem[53] = 2'b0;
        mem[54] = 2'b0;
        mem[55] = 2'b0;
        mem[56] = 2'b1;
        mem[57] = 2'b1;
        mem[58] = 2'b1;
        mem[59] = 2'b1;
        mem[60] = 2'b1;
        mem[61] = 2'b1;
        mem[62] = 2'b1;
        mem[63] = 2'b1;
      end
      1'b1: begin
        mem[0] = 2'b1;	mem[1] = 2'b1;	mem[2] = 2'b1;	mem[3] = 2'b1;	mem[4] = 2'b1;	mem[5] = 2'b1;	mem[6] = 2'b1;	mem[7] = 2'b1;
        mem[8] = 2'b1;	mem[9] = 2'b1;	mem[10] = 2'b0;	mem[11] = 2'b0;	mem[12] = 2'b0;	mem[13] = 2'b1;	mem[14] = 2'b0;	mem[15] = 2'b1;
        mem[16] = 2'b1;	mem[17] = 2'b0;	mem[18] = 2'b0;	mem[19] = 2'b1;	mem[20] = 2'b0;	mem[21] = 2'b1;	mem[22] = 2'b0;	mem[23] = 2'b1;
        mem[24] = 2'b1;	mem[25] = 2'b1;	mem[26] = 2'b0;	mem[27] = 2'b1;	mem[28] = 2'b0;	mem[29] = 2'b0;	mem[30] = 2'b0;	mem[31] = 2'b0;
        mem[32] = 2'b1;	mem[33] = 2'b1;	mem[34] = 2'b0;	mem[35] = 2'b1;	mem[36] = 2'b0;	mem[37] = 2'b1;	mem[38] = 2'b0;	mem[39] = 2'b1;
        mem[40] = 2'b1;	mem[41] = 2'b0;	mem[42] = 2'b0;	mem[43] = 2'b1;	mem[44] = 2'b0;	mem[45] = 2'b1;	mem[46] = 2'b1;	mem[47] = 2'b1;
        mem[48] = 2'b10;	mem[49] = 2'b0;	mem[50] = 2'b1;	mem[51] = 2'b1;	mem[52] = 2'b0;	mem[53] = 2'b0;	mem[54] = 2'b0;	mem[55] = 2'b1;
        mem[56] = 2'b1;	mem[57] = 2'b1;	mem[58] = 2'b1;	mem[59] = 2'b1;	mem[60] = 2'b1;	mem[61] = 2'b1;	mem[62] = 2'b1;	mem[63] = 2'b1;
      end
    endcase
  end
  else if (command)
    mem[address] = mem[address];
  else
    mem[address] = data_in;
end

endmodule // memory

Maze_t.v
module Maze_test();

reg clk;
initial clk = 1'b0;
always clk = #1 ~clk;

initial
begin
$dumpfile("Maze_test.vcd");
$dumpvars(0, Maze_test);
end

tri [5:0] address;
tri commend;
tri [1:0] data;

reg timeout;
reg [3:0] key_value;

wire NVcommend,timecheckstop;

wire [7:0] number;

memory memory1(
  clk,
  nst,
  address,
  commend,
  data
);

commend commend1(
  .clk(clk),
  .key_value(key_value),
  .nst(nst),
  .address(address),
  .commend(commend),
  .NVcommend(NVcommend),
  .data(data),
  .timeout(timeout),
  .timecheckstop(timecheckstop)
);

initial begin
    timeout = 1'b0;
    key_value = 0;
    #300 key_value = 10;
    #300 key_value = 0;
    #300 key_value = 7;
    #300 key_value = 0;
    #300 key_value = 7;
    #300 key_value = 0;
    #300 key_value = 7;
    #300 key_value = 0;
    #300 key_value = 7;
    #300 key_value = 0;
    #300 key_value = 7;
    #300 key_value = 0;
    #300 key_value = 7;
    #300 key_value = 0;
    #300 timeout = 1'b1;
    #4000 $finish;
end

endmodule // Maze_test

Maze_test.vcd
$date
	Thu Dec 27 09:07:25 2018
$end
$version
	Icarus Verilog
$end
$timescale
	1s
$end
$scope module Maze_test $end
$var wire 2 ! data [1:0] $end
$var wire 1 " nst $end
$var wire 1 # timecheckstop $end
$var wire 1 $ commend $end
$var wire 6 % address [5:0] $end
$var wire 1 & NVcommend $end
$var reg 1 ' clk $end
$var reg 4 ( key_value [3:0] $end
$var reg 1 ) timeout $end
$scope module commend1 $end
$var wire 1 ' clk $end
$var wire 2 * data [1:0] $end
$var wire 4 + key_value [3:0] $end
$var wire 1 " nst $end
$var wire 1 ) timeout $end
$var wire 2 , data_in [1:0] $end
$var reg 1 & NVcommend $end
$var reg 2 - OtherStatus [1:0] $end
$var reg 6 . address [5:0] $end
$var reg 21 / cnt [20:0] $end
$var reg 1 $ commend $end
$var reg 2 0 data_out [1:0] $end
$var reg 6 1 k [5:0] $end
$var reg 4 2 key_value_tmp [3:0] $end
$var reg 5 3 status [4:0] $end
$var reg 1 # timecheckstop $end
$upscope $end
$scope module memory1 $end
$var wire 6 4 address [5:0] $end
$var wire 1 ' clk $end
$var wire 1 $ command $end
$var wire 2 5 data [1:0] $end
$var wire 1 " rst $end
$var wire 2 6 data_in [1:0] $end
$var reg 1 7 count $end
$upscope $end
$upscope $end
$enddefinitions $end
#0
$dumpvars
07
bx 6
bx 5
bz 4
b0 3
bz 2
b0 1
bx 0
b0 /
bz .
b0 -
bx ,
b0 +
bx *
0)
b0 (
0'
1&
bz %
z$
1#
z"
bx !
$end
#1
17
0#
1'
#2
0'
#3
07
1'
#4
0'
#5
17
1'
#6
0'
#7
07
1'
#8
0'
#9
17
1'
#10
0'
#11
07
1'
#12
0'
#13
17
1'
#14
0'
#15
07
1'
#16
0'
#17
17
1'
#18
0'
#19
07
1'
#20
0'
#21
17
1'
#22
0'
#23
07
1'
#24
0'
#25
17
1'
#26
0'
#27
07
1'
#28
0'
#29
17
1'
#30
0'
#31
07
1'
#32
0'
#33
17
1'
#34
0'
#35
07
1'
#36
0'
#37
17
1'
#38
0'
#39
07
1'
#40
0'
#41
17
1'
#42
0'
#43
07
1'
#44
0'
#45
17
1'
#46
0'
#47
07
1'
#48
0'
#49
17
1'
#50
0'
#51
07
1'
#52
0'
#53
17
1'
#54
0'
#55
07
1'
#56
0'
#57
17
1'
#58
0'
#59
07
1'
#60
0'
#61
17
1'
#62
0'
#63
07
1'
#64
0'
#65
17
1'
#66
0'
#67
07
1'
#68
0'
#69
17
1'
#70
0'
#71
07
1'
#72
0'
#73
17
1'
#74
0'
#75
07
1'
#76
0'
#77
17
1'
#78
0'
#79
07
1'
#80
0'
#81
17
1'
#82
0'
#83
07
1'
#84
0'
#85
17
1'
#86
0'
#87
07
1'
#88
0'
#89
17
1'
#90
0'
#91
07
1'
#92
0'
#93
17
1'
#94
0'
#95
07
1'
#96
0'
#97
17
1'
#98
0'
#99
07
1'
#100
0'
#101
17
1'
#102
0'
#103
07
1'
#104
0'
#105
17
1'
#106
0'
#107
07
1'
#108
0'
#109
17
1'
#110
0'
#111
07
1'
#112
0'
#113
17
1'
#114
0'
#115
07
1'
#116
0'
#117
17
1'
#118
0'
#119
07
1'
#120
0'
#121
17
1'
#122
0'
#123
07
1'
#124
0'
#125
17
1'
#126
0'
#127
07
1'
#128
0'
#129
17
1'
#130
0'
#131
07
1'
#132
0'
#133
17
1'
#134
0'
#135
07
1'
#136
0'
#137
17
1'
#138
0'
#139
07
1'
#140
0'
#141
17
1'
#142
0'
#143
07
1'
#144
0'
#145
17
1'
#146
0'
#147
07
1'
#148
0'
#149
17
1'
#150
0'
#151
07
1'
#152
0'
#153
17
1'
#154
0'
#155
07
1'
#156
0'
#157
17
1'
#158
0'
#159
07
1'
#160
0'
#161
17
1'
#162
0'
#163
07
1'
#164
0'
#165
17
1'
#166
0'
#167
07
1'
#168
0'
#169
17
1'
#170
0'
#171
07
1'
#172
0'
#173
17
1'
#174
0'
#175
07
1'
#176
0'
#177
17
1'
#178
0'
#179
07
1'
#180
0'
#181
17
1'
#182
0'
#183
07
1'
#184
0'
#185
17
1'
#186
0'
#187
07
1'
#188
0'
#189
17
1'
#190
0'
#191
07
1'
#192
0'
#193
17
1'
#194
0'
#195
07
1'
#196
0'
#197
17
1'
#198
0'
#199
07
1'
#200
0'
#201
17
1'
#202
0'
#203
07
1'
#204
0'
#205
17
1'
#206
0'
#207
07
1'
#208
0'
#209
17
1'
#210
0'
#211
07
1'
#212
0'
#213
17
1'
#214
0'
#215
07
1'
#216
0'
#217
17
1'
#218
0'
#219
07
1'
#220
0'
#221
17
1'
#222
0'
#223
07
1'
#224
0'
#225
17
1'
#226
0'
#227
07
1'
#228
0'
#229
17
1'
#230
0'
#231
07
1'
#232
0'
#233
17
1'
#234
0'
#235
07
1'
#236
0'
#237
17
1'
#238
0'
#239
07
1'
#240
0'
#241
17
1'
#242
0'
#243
07
1'
#244
0'
#245
17
1'
#246
0'
#247
07
1'
#248
0'
#249
17
1'
#250
0'
#251
07
1'
#252
0'
#253
17
1'
#254
0'
#255
07
1'
#256
0'
#257
17
1'
#258
0'
#259
07
1'
#260
0'
#261
17
1'
#262
0'
#263
07
1'
#264
0'
#265
17
1'
#266
0'
#267
07
1'
#268
0'
#269
17
1'
#270
0'
#271
07
1'
#272
0'
#273
17
1'
#274
0'
#275
07
1'
#276
0'
#277
17
1'
#278
0'
#279
07
1'
#280
0'
#281
17
1'
#282
0'
#283
07
1'
#284
0'
#285
17
1'
#286
0'
#287
07
1'
#288
0'
#289
17
1'
#290
0'
#291
07
1'
#292
0'
#293
17
1'
#294
0'
#295
07
1'
#296
0'
#297
17
1'
#298
0'
#299
07
1'
#300
0'
b1010 (
b1010 +
#301
b1 ,
bz 6
b1 !
b1 *
b1 5
17
b1 3
1$
b0 %
b0 .
b0 4
0&
b1010 2
1'
#302
0'
#303
b1 %
b1 .
b1 4
b1 1
07
1'
#304
0'
#305
17
b10 %
b10 .
b10 4
b10 1
1'
#306
0'
#307
b11 %
b11 .
b11 4
b11 1
07
1'
#308
0'
#309
17
b100 %
b100 .
b100 4
b100 1
1'
#310
0'
#311
b101 %
b101 .
b101 4
b101 1
07
1'
#312
0'
#313
17
b110 %
b110 .
b110 4
b110 1
1'
#314
0'
#315
b111 %
b111 .
b111 4
b111 1
07
1'
#316
0'
#317
17
b1000 %
b1000 .
b1000 4
b1000 1
1'
#318
0'
#319
b1001 %
b1001 .
b1001 4
b1001 1
07
1'
#320
0'
#321
17
b1010 %
b1010 .
b1010 4
b1010 1
1'
#322
0'
#323
b1011 %
b1011 .
b1011 4
b1011 1
07
1'
#324
0'
#325
b0 ,
b0 !
b0 *
b0 5
17
b1100 %
b1100 .
b1100 4
b1100 1
1'
#326
0'
#327
b1101 %
b1101 .
b1101 4
b1101 1
07
1'
#328
0'
#329
17
b1110 %
b1110 .
b1110 4
b1110 1
1'
#330
0'
#331
b1 ,
b1 !
b1 *
b1 5
b1111 %
b1111 .
b1111 4
b1111 1
07
1'
#332
0'
#333
17
b10000 %
b10000 .
b10000 4
b10000 1
1'
#334
0'
#335
b0 ,
b0 !
b0 *
b0 5
b10001 %
b10001 .
b10001 4
b10001 1
07
1'
#336
0'
#337
17
b10010 %
b10010 .
b10010 4
b10010 1
1'
#338
0'
#339
b10011 %
b10011 .
b10011 4
b10011 1
07
1'
#340
0'
#341
17
b10100 %
b10100 .
b10100 4
b10100 1
1'
#342
0'
#343
b1 ,
b1 !
b1 *
b1 5
b10101 %
b10101 .
b10101 4
b10101 1
07
1'
#344
0'
#345
b0 ,
b0 !
b0 *
b0 5
17
b10110 %
b10110 .
b10110 4
b10110 1
1'
#346
0'
#347
b1 ,
b1 !
b1 *
b1 5
b10111 %
b10111 .
b10111 4
b10111 1
07
1'
#348
0'
#349
17
b11000 %
b11000 .
b11000 4
b11000 1
1'
#350
0'
#351
b0 ,
b0 !
b0 *
b0 5
b11001 %
b11001 .
b11001 4
b11001 1
07
1'
#352
0'
#353
b1 ,
b1 !
b1 *
b1 5
17
b11010 %
b11010 .
b11010 4
b11010 1
1'
#354
0'
#355
b0 ,
b0 !
b0 *
b0 5
b11011 %
b11011 .
b11011 4
b11011 1
07
1'
#356
0'
#357
b1 ,
b1 !
b1 *
b1 5
17
b11100 %
b11100 .
b11100 4
b11100 1
1'
#358
0'
#359
b11101 %
b11101 .
b11101 4
b11101 1
07
1'
#360
0'
#361
b0 ,
b0 !
b0 *
b0 5
17
b11110 %
b11110 .
b11110 4
b11110 1
1'
#362
0'
#363
b1 ,
b1 !
b1 *
b1 5
b11111 %
b11111 .
b11111 4
b11111 1
07
1'
#364
0'
#365
17
b100000 %
b100000 .
b100000 4
b100000 1
1'
#366
0'
#367
b0 ,
b0 !
b0 *
b0 5
b100001 %
b100001 .
b100001 4
b100001 1
07
1'
#368
0'
#369
b1 ,
b1 !
b1 *
b1 5
17
b100010 %
b100010 .
b100010 4
b100010 1
1'
#370
0'
#371
b0 ,
b0 !
b0 *
b0 5
b100011 %
b100011 .
b100011 4
b100011 1
07
1'
#372
0'
#373
b1 ,
b1 !
b1 *
b1 5
17
b100100 %
b100100 .
b100100 4
b100100 1
1'
#374
0'
#375
b0 ,
b0 !
b0 *
b0 5
b100101 %
b100101 .
b100101 4
b100101 1
07
1'
#376
0'
#377
17
b100110 %
b100110 .
b100110 4
b100110 1
1'
#378
0'
#379
b1 ,
b1 !
b1 *
b1 5
b100111 %
b100111 .
b100111 4
b100111 1
07
1'
#380
0'
#381
17
b101000 %
b101000 .
b101000 4
b101000 1
1'
#382
0'
#383
b0 ,
b0 !
b0 *
b0 5
b101001 %
b101001 .
b101001 4
b101001 1
07
1'
#384
0'
#385
b1 ,
b1 !
b1 *
b1 5
17
b101010 %
b101010 .
b101010 4
b101010 1
1'
#386
0'
#387
b0 ,
b0 !
b0 *
b0 5
b101011 %
b101011 .
b101011 4
b101011 1
07
1'
#388
0'
#389
b1 ,
b1 !
b1 *
b1 5
17
b101100 %
b101100 .
b101100 4
b101100 1
1'
#390
0'
#391
b0 ,
b0 !
b0 *
b0 5
b101101 %
b101101 .
b101101 4
b101101 1
07
1'
#392
0'
#393
b1 ,
b1 !
b1 *
b1 5
17
b101110 %
b101110 .
b101110 4
b101110 1
1'
#394
0'
#395
b101111 %
b101111 .
b101111 4
b101111 1
07
1'
#396
0'
#397
b10 ,
b10 !
b10 *
b10 5
17
b110000 %
b110000 .
b110000 4
b110000 1
1'
#398
0'
#399
b10 3
07
1'
#400
0'
#401
b0 ,
b0 !
b0 *
b0 5
17
b11 3
b110001 %
b110001 .
b110001 4
1'
#402
0'
#403
b10 6
bz ,
b10 !
b10 *
b10 5
b100 3
b10 0
0$
07
1'
#404
0'
#405
b0 6
b0 !
b0 *
b0 5
17
b0 1
b101 3
b0 0
b110000 %
b110000 .
b110000 4
1'
#406
0'
#407
bx 6
bx ,
bx !
bx *
bx 5
1&
z$
bz %
bz .
bz 4
b0 3
07
1'
#408
0'
#409
17
1'
#410
0'
#411
07
1'
#412
0'
#413
17
1'
#414
0'
#415
07
1'
#416
0'
#417
17
1'
#418
0'
#419
07
1'
#420
0'
#421
17
1'
#422
0'
#423
07
1'
#424
0'
#425
17
1'
#426
0'
#427
07
1'
#428
0'
#429
17
1'
#430
0'
#431
07
1'
#432
0'
#433
17
1'
#434
0'
#435
07
1'
#436
0'
#437
17
1'
#438
0'
#439
07
1'
#440
0'
#441
17
1'
#442
0'
#443
07
1'
#444
0'
#445
17
1'
#446
0'
#447
07
1'
#448
0'
#449
17
1'
#450
0'
#451
07
1'
#452
0'
#453
17
1'
#454
0'
#455
07
1'
#456
0'
#457
17
1'
#458
0'
#459
07
1'
#460
0'
#461
17
1'
#462
0'
#463
07
1'
#464
0'
#465
17
1'
#466
0'
#467
07
1'
#468
0'
#469
17
1'
#470
0'
#471
07
1'
#472
0'
#473
17
1'
#474
0'
#475
07
1'
#476
0'
#477
17
1'
#478
0'
#479
07
1'
#480
0'
#481
17
1'
#482
0'
#483
07
1'
#484
0'
#485
17
1'
#486
0'
#487
07
1'
#488
0'
#489
17
1'
#490
0'
#491
07
1'
#492
0'
#493
17
1'
#494
0'
#495
07
1'
#496
0'
#497
17
1'
#498
0'
#499
07
1'
#500
0'
#501
17
1'
#502
0'
#503
07
1'
#504
0'
#505
17
1'
#506
0'
#507
07
1'
#508
0'
#509
17
1'
#510
0'
#511
07
1'
#512
0'
#513
17
1'
#514
0'
#515
07
1'
#516
0'
#517
17
1'
#518
0'
#519
07
1'
#520
0'
#521
17
1'
#522
0'
#523
07
1'
#524
0'
#525
17
1'
#526
0'
#527
07
1'
#528
0'
#529
17
1'
#530
0'
#531
07
1'
#532
0'
#533
17
1'
#534
0'
#535
07
1'
#536
0'
#537
17
1'
#538
0'
#539
07
1'
#540
0'
#541
17
1'
#542
0'
#543
07
1'
#544
0'
#545
17
1'
#546
0'
#547
07
1'
#548
0'
#549
17
1'
#550
0'
#551
07
1'
#552
0'
#553
17
1'
#554
0'
#555
07
1'
#556
0'
#557
17
1'
#558
0'
#559
07
1'
#560
0'
#561
17
1'
#562
0'
#563
07
1'
#564
0'
#565
17
1'
#566
0'
#567
07
1'
#568
0'
#569
17
1'
#570
0'
#571
07
1'
#572
0'
#573
17
1'
#574
0'
#575
07
1'
#576
0'
#577
17
1'
#578
0'
#579
07
1'
#580
0'
#581
17
1'
#582
0'
#583
07
1'
#584
0'
#585
17
1'
#586
0'
#587
07
1'
#588
0'
#589
17
1'
#590
0'
#591
07
1'
#592
0'
#593
17
1'
#594
0'
#595
07
1'
#596
0'
#597
17
1'
#598
0'
#599
07
1'
#600
0'
b0 (
b0 +
#601
17
bz 2
1'
#602
0'
#603
07
1'
#604
0'
#605
17
1'
#606
0'
#607
07
1'
#608
0'
#609
17
1'
#610
0'
#611
07
1'
#612
0'
#613
17
1'
#614
0'
#615
07
1'
#616
0'
#617
17
1'
#618
0'
#619
07
1'
#620
0'
#621
17
1'
#622
0'
#623
07
1'
#624
0'
#625
17
1'
#626
0'
#627
07
1'
#628
0'
#629
17
1'
#630
0'
#631
07
1'
#632
0'
#633
17
1'
#634
0'
#635
07
1'
#636
0'
#637
17
1'
#638
0'
#639
07
1'
#640
0'
#641
17
1'
#642
0'
#643
07
1'
#644
0'
#645
17
1'
#646
0'
#647
07
1'
#648
0'
#649
17
1'
#650
0'
#651
07
1'
#652
0'
#653
17
1'
#654
0'
#655
07
1'
#656
0'
#657
17
1'
#658
0'
#659
07
1'
#660
0'
#661
17
1'
#662
0'
#663
07
1'
#664
0'
#665
17
1'
#666
0'
#667
07
1'
#668
0'
#669
17
1'
#670
0'
#671
07
1'
#672
0'
#673
17
1'
#674
0'
#675
07
1'
#676
0'
#677
17
1'
#678
0'
#679
07
1'
#680
0'
#681
17
1'
#682
0'
#683
07
1'
#684
0'
#685
17
1'
#686
0'
#687
07
1'
#688
0'
#689
17
1'
#690
0'
#691
07
1'
#692
0'
#693
17
1'
#694
0'
#695
07
1'
#696
0'
#697
17
1'
#698
0'
#699
07
1'
#700
0'
#701
17
1'
#702
0'
#703
07
1'
#704
0'
#705
17
1'
#706
0'
#707
07
1'
#708
0'
#709
17
1'
#710
0'
#711
07
1'
#712
0'
#713
17
1'
#714
0'
#715
07
1'
#716
0'
#717
17
1'
#718
0'
#719
07
1'
#720
0'
#721
17
1'
#722
0'
#723
07
1'
#724
0'
#725
17
1'
#726
0'
#727
07
1'
#728
0'
#729
17
1'
#730
0'
#731
07
1'
#732
0'
#733
17
1'
#734
0'
#735
07
1'
#736
0'
#737
17
1'
#738
0'
#739
07
1'
#740
0'
#741
17
1'
#742
0'
#743
07
1'
#744
0'
#745
17
1'
#746
0'
#747
07
1'
#748
0'
#749
17
1'
#750
0'
#751
07
1'
#752
0'
#753
17
1'
#754
0'
#755
07
1'
#756
0'
#757
17
1'
#758
0'
#759
07
1'
#760
0'
#761
17
1'
#762
0'
#763
07
1'
#764
0'
#765
17
1'
#766
0'
#767
07
1'
#768
0'
#769
17
1'
#770
0'
#771
07
1'
#772
0'
#773
17
1'
#774
0'
#775
07
1'
#776
0'
#777
17
1'
#778
0'
#779
07
1'
#780
0'
#781
17
1'
#782
0'
#783
07
1'
#784
0'
#785
17
1'
#786
0'
#787
07
1'
#788
0'
#789
17
1'
#790
0'
#791
07
1'
#792
0'
#793
17
1'
#794
0'
#795
07
1'
#796
0'
#797
17
1'
#798
0'
#799
07
1'
#800
0'
#801
17
1'
#802
0'
#803
07
1'
#804
0'
#805
17
1'
#806
0'
#807
07
1'
#808
0'
#809
17
1'
#810
0'
#811
07
1'
#812
0'
#813
17
1'
#814
0'
#815
07
1'
#816
0'
#817
17
1'
#818
0'
#819
07
1'
#820
0'
#821
17
1'
#822
0'
#823
07
1'
#824
0'
#825
17
1'
#826
0'
#827
07
1'
#828
0'
#829
17
1'
#830
0'
#831
07
1'
#832
0'
#833
17
1'
#834
0'
#835
07
1'
#836
0'
#837
17
1'
#838
0'
#839
07
1'
#840
0'
#841
17
1'
#842
0'
#843
07
1'
#844
0'
#845
17
1'
#846
0'
#847
07
1'
#848
0'
#849
17
1'
#850
0'
#851
07
1'
#852
0'
#853
17
1'
#854
0'
#855
07
1'
#856
0'
#857
17
1'
#858
0'
#859
07
1'
#860
0'
#861
17
1'
#862
0'
#863
07
1'
#864
0'
#865
17
1'
#866
0'
#867
07
1'
#868
0'
#869
17
1'
#870
0'
#871
07
1'
#872
0'
#873
17
1'
#874
0'
#875
07
1'
#876
0'
#877
17
1'
#878
0'
#879
07
1'
#880
0'
#881
17
1'
#882
0'
#883
07
1'
#884
0'
#885
17
1'
#886
0'
#887
07
1'
#888
0'
#889
17
1'
#890
0'
#891
07
1'
#892
0'
#893
17
1'
#894
0'
#895
07
1'
#896
0'
#897
17
1'
#898
0'
#899
07
1'
#900
0'
b111 (
b111 +
#901
b1 ,
bz 6
b1 !
b1 *
b1 5
17
b1 3
1$
b0 %
b0 .
b0 4
0&
b111 2
1'
#902
0'
#903
b1 %
b1 .
b1 4
b1 1
07
1'
#904
0'
#905
17
b10 %
b10 .
b10 4
b10 1
1'
#906
0'
#907
b11 %
b11 .
b11 4
b11 1
07
1'
#908
0'
#909
17
b100 %
b100 .
b100 4
b100 1
1'
#910
0'
#911
b101 %
b101 .
b101 4
b101 1
07
1'
#912
0'
#913
17
b110 %
b110 .
b110 4
b110 1
1'
#914
0'
#915
b111 %
b111 .
b111 4
b111 1
07
1'
#916
0'
#917
17
b1000 %
b1000 .
b1000 4
b1000 1
1'
#918
0'
#919
b1001 %
b1001 .
b1001 4
b1001 1
07
1'
#920
0'
#921
17
b1010 %
b1010 .
b1010 4
b1010 1
1'
#922
0'
